pylabinstruments/__init__.py
pylabinstruments/base.py
pylabinstruments/function_generator.py
pylabinstruments/keithly_smu.py
pylabinstruments/multimeter.py
pylabinstruments/network_analyzer.py
pylabinstruments/oscilloscope.py
pylabinstruments/py.typed
pylabinstruments/smu.py
pylabinstruments/supply.py
pylabinstruments/temperature_controller.py
pylabinstruments/temperature_sensor.py
pylabinstruments/thermonics.py
pylabinstruments/utils/__init__.py
pylabinstruments/utils/decorators.py
pylabinstruments/utils/logger.py
pylabinstruments/utils/utilities.py
pylabinstruments-0.1.0.dist-info/licenses/LICENSE
pylabinstruments-0.1.0.dist-info/METADATA
pylabinstruments-0.1.0.dist-info/WHEEL
pylabinstruments-0.1.0.dist-info/top_level.txt
pylabinstruments-0.1.0.dist-info/RECORD
