Metadata-Version: 2.4
Name: pylabinstruments
Version: 0.1.0
Summary: A Python library for interfacing with various laboratory instruments through GPIB/VISA connections
Author-email: Tyler Rothenberg <rothenbergt@gmail.com>
License-Expression: MIT
Project-URL: Homepage, https://github.com/rothenbergt/pylabinstruments
Project-URL: Bug Tracker, https://github.com/rothenbergt/pylabinstruments/issues
Classifier: Development Status :: 4 - Beta
Classifier: Intended Audience :: Science/Research
Classifier: Programming Language :: Python :: 3
Classifier: Programming Language :: Python :: 3.10
Classifier: Programming Language :: Python :: 3.11
Classifier: Programming Language :: Python :: 3.12
Classifier: Topic :: Scientific/Engineering :: Interface Engine/Protocol Translator
Requires-Python: >=3.10
License-File: LICENSE
Requires-Dist: pyvisa>=1.11.0
Requires-Dist: pyvisa-py>=0.5.0
Requires-Dist: numpy>=1.19.0
Requires-Dist: pandas>=1.0.0
Requires-Dist: matplotlib>=3.3.0
Requires-Dist: pillow>=6.2.0
Provides-Extra: gui
Requires-Dist: PySimpleGUI>=4.40.0; extra == "gui"
Provides-Extra: dev
Requires-Dist: pytest>=7.0.0; extra == "dev"
Requires-Dist: pytest-cov>=4.0.0; extra == "dev"
Requires-Dist: pytest-mock>=3.10.0; extra == "dev"
Requires-Dist: pytest-xdist>=3.3.0; extra == "dev"
Requires-Dist: flake8>=6.0.0; extra == "dev"
Requires-Dist: pre-commit>=3.6.0; extra == "dev"
Requires-Dist: ruff>=0.5.0; extra == "dev"
Dynamic: license-file
